README.md
setup.py
getwallpapers/__init__.py
getwallpapers/downloader.py
getwallpapers_downloader.egg-info/PKG-INFO
getwallpapers_downloader.egg-info/SOURCES.txt
getwallpapers_downloader.egg-info/dependency_links.txt
getwallpapers_downloader.egg-info/requires.txt
getwallpapers_downloader.egg-info/top_level.txt