Metadata-Version: 2.1
Name: getwallpapers-downloader
Version: 0.0.1
Summary: Download wallpapers from getwallpapers.com
Home-page: https://github.com/falcon-head/getwallpapers-downloader
Author: Aptha K S
Author-email: iamuraptha@gmail.com
License: MIT
Platform: UNKNOWN
Classifier: License :: OSI Approved :: MIT License
Classifier: Programming Language :: Python :: 3.6
Requires-Python: >=3.6
